hexora/__init__.py
hexora/_hexora.cpython-39-darwin.so
hexora/py.typed
hexora-0.2.2.dist-info/RECORD
hexora-0.2.2.dist-info/WHEEL
hexora-0.2.2.dist-info/entry_points.txt
hexora-0.2.2.dist-info/top_level.txt
hexora-0.2.2.dist-info/METADATA
hexora-0.2.2.dist-info/licenses/LICENSE
