Metadata-Version: 2.4
Name: hexora
Version: 0.2.2
Summary: Static analysis of malicous Python scripts.
Author-email: Artem Golubin <me@rushter.com>
License-Expression: MIT
Project-URL: Homepage, https://github.com/rushter/hexora
Project-URL: Repository, https://github.com/rushter/hexora
Project-URL: Documentation, https://github.com/rushter/hexora/blob/main/README.md
Requires-Python: >=3.9
License-File: LICENSE
Dynamic: license-file
